data_documenter/__init__.py
data_documenter/metadocs.py
data_documenter/pandera_plugin.py
data_documenter/templates/index.md
data_documenter/templates/mkdocs.yml
data_documenter/utils.py
data_documenter-0.3.4.dist-info/LICENSE
data_documenter-0.3.4.dist-info/METADATA
data_documenter-0.3.4.dist-info/WHEEL
data_documenter-0.3.4.dist-info/RECORD
