Metadata-Version: 2.1
Name: data-documenter
Version: 0.3.4
Summary: 
Author: Samarin Aleksei
Author-email: liotbiu1@gmail.com
Requires-Python: >=3.10,<4.0
Classifier: Programming Language :: Python :: 3
Classifier: Programming Language :: Python :: 3.10
Classifier: Programming Language :: Python :: 3.11
Classifier: Programming Language :: Python :: 3.12
Requires-Dist: mdutils (>=1.6.0,<2.0.0)
Requires-Dist: mkdocs-material (>=9.5.7,<10.0.0)
Requires-Dist: pandas (>=2.2.0,<3.0.0)
Requires-Dist: pandera (>=0.18.0,<0.19.0)
Requires-Dist: pyyaml (>=6.0.1,<7.0.0)
